<?xml version="1.0" encoding="utf-8" ?>
<dwsync>
<file name="admin.php" server="23.229.204.232/public_html/development/" local="130612244721418981" remote="130611902400000000" Dst="0" />
<file name="control.php" server="23.229.204.232/public_html/development/" local="130612239168665897" remote="130611902400000000" Dst="0" />
<file name="settings.php" server="23.229.204.232/public_html/development/" local="130597462020038381" remote="130595435400000000" Dst="0" />
<file name="users.php" server="23.229.204.232/public_html/development/" local="130612245183926808" remote="130611902400000000" Dst="0" />
<file name="reports.php" server="23.229.204.232/public_html/development/" local="130612251932654971" remote="130611902400000000" Dst="0" />
<file name="user_types.php" server="23.229.204.232/public_html/development/" local="130597418403047922" remote="130602388800000000" Dst="0" />
<file name="admin.php" server="148.251.2.43/public_html/development/" local="130612244740000000" remote="130650275400000000" Dst="0" />
<file name="control.php" server="148.251.2.43/public_html/development/" local="130612239180000000" remote="130650275400000000" Dst="0" />
<file name="reports.php" server="148.251.2.43/public_html/development/" local="130612251940000000" remote="130650275400000000" Dst="0" />
<file name="settings.php" server="148.251.2.43/public_html/development/" local="130597462040000000" remote="130650275400000000" Dst="0" />
<file name="user_types.php" server="148.251.2.43/public_html/development/" local="130597418420000000" remote="130650275400000000" Dst="0" />
<file name="users.php" server="148.251.2.43/public_html/development/" local="130613595440000000" remote="130650275400000000" Dst="0" />
<file name="admin.php" server="148.251.2.43/public_html/" local="130612244740000000" remote="130656301200000000" Dst="0" />
<file name="control.php" server="148.251.2.43/public_html/" local="130612239180000000" remote="130656301200000000" Dst="0" />
<file name="reports.php" server="148.251.2.43/public_html/" local="130612251940000000" remote="130656301200000000" Dst="0" />
<file name="settings.php" server="148.251.2.43/public_html/" local="130597462040000000" remote="130656301800000000" Dst="0" />
<file name="users.php" server="148.251.2.43/public_html/" local="130613595440000000" remote="130656301800000000" Dst="0" />
<file name="user_types.php" server="148.251.2.43/public_html/" local="130597418420000000" remote="130656301800000000" Dst="0" />
<file name="advertising.php" server="janta254.co.ke/public_html/" local="131098692703458930" remote="131098695600000000" Dst="0" />
<file name="advertising.php" server="choto.co.ke//var/www/html/" local="131177100261184666" remote="131177100000000000" Dst="0" />
</dwsync>